aasp/__init__.py
aasp/callback.py
aasp/client.py
aasp/exceptions.py
aasp/types.py
aasp_sdk-0.1.0.dist-info/METADATA
aasp_sdk-0.1.0.dist-info/WHEEL
aasp_sdk-0.1.0.dist-info/RECORD
