Metadata-Version: 2.4
Name: aasp-sdk
Version: 0.1.0
Summary: AI Agent Security Platform SDK - Secure your LangChain agents with policy enforcement
Project-URL: Homepage, https://aasp.dev
Project-URL: Documentation, https://docs.aasp.dev
Project-URL: Repository, https://github.com/aasp-dev/aasp-python
Author-email: AASP Team <hello@aasp.dev>
License-Expression: MIT
Keywords: agent,ai,governance,langchain,llm,policy,security
Classifier: Development Status :: 3 - Alpha
Classifier: Intended Audience :: Developers
Classifier: License :: OSI Approved :: MIT License
Classifier: Programming Language :: Python :: 3
Classifier: Programming Language :: Python :: 3.10
Classifier: Programming Language :: Python :: 3.11
Classifier: Programming Language :: Python :: 3.12
Classifier: Topic :: Security
Classifier: Topic :: Software Development :: Libraries :: Python Modules
Requires-Python: >=3.10
Requires-Dist: httpx>=0.25.0
Provides-Extra: dev
Requires-Dist: mypy>=1.0.0; extra == 'dev'
Requires-Dist: pytest-asyncio>=0.21.0; extra == 'dev'
Requires-Dist: pytest-httpx>=0.22.0; extra == 'dev'
Requires-Dist: pytest>=7.0.0; extra == 'dev'
Requires-Dist: ruff>=0.1.0; extra == 'dev'
Provides-Extra: langchain
Requires-Dist: langchain-core>=0.1.0; extra == 'langchain'
